{
  "project_info": {
    "project_number": "187086706775",
    "project_id": "password-manager-89a69",
    "storage_bucket": "password-manager-89a69.firebasestorage.app"
  },
  "client": [
    {
      "client_info": {
        "mobilesdk_app_id": "1:187086706775:android:c41289493b81b472ac2b12",
        "android_client_info": {
          "package_name": "com.example.password_manager"
        }
      },
      "oauth_client": [
        {
          "client_id": "187086706775-e1b17qkt5itipvn5hpki047ml0mcfkaq.apps.googleusercontent.com",
          "client_type": 1,
          "android_info": {
            "package_name": "com.example.password_manager",
            "certificate_hash": "0c5dd6087f0c1f6762292762f8eab9c7f5367db0"
          }
        }
      ],
      "api_key": [
        {
          "current_key": "AIzaSyAhRoPsDHl26t9ErXb2os9EBXA_q1-9ORU"
        }
      ],
      "services": {
        "appinvite_service": {
          "other_platform_oauth_client": []
        }
      }
    }
  ],
  "configuration_version": "1"
}